is_ipfs/__init__.py
is_ipfs/__main__.py
is_ipfs/is_ipfs.py
is_ipfs/py.typed
py_is_ipfs-0.6.0.dist-info/LICENSE
py_is_ipfs-0.6.0.dist-info/METADATA
py_is_ipfs-0.6.0.dist-info/WHEEL
py_is_ipfs-0.6.0.dist-info/top_level.txt
py_is_ipfs-0.6.0.dist-info/RECORD
