Metadata-Version: 2.1
Name: py-is_ipfs
Version: 0.6.0
Summary: Python library to identify valid IPFS resources
Home-page: https://github.com/Barabazs/py-is_ipfs
Author: Barabazs
License: MIT
Classifier: Development Status :: 4 - Beta
Classifier: Intended Audience :: Developers
Classifier: License :: OSI Approved :: MIT License
Classifier: Natural Language :: English
Classifier: Programming Language :: Python :: 3 :: Only
Classifier: Programming Language :: Python :: 3.9
Classifier: Programming Language :: Python :: 3.10
Classifier: Programming Language :: Python :: 3.11
License-File: LICENSE
Requires-Dist: py-cid<1.0.0,>=0.3.0
Requires-Dist: py-multibase<2.0.0,>=1.0.3
